{"name": "Absolute Law", "slug": "absolute-law", "scryfall_id": "59d1f05b-f165-47c7-8a78-3b60ee3298ca", "image_uri": "https://cards.scryfall.io/normal/front/5/9/59d1f05b-f165-47c7-8a78-3b60ee3298ca.jpg", "type_line": "Enchantment", "total_decks": 3, "total_pct": 0.2, "color_identity": ["W"], "commanders": [{"name": "Errant and Giada", "id": "errant-and-giada", "image_uri": "https://cards.scryfall.io/normal/front/5/4/54aa2d03-7713-44d4-8fca-45c6f77b174b.jpg", "inclusion_pct": 100.0, "synergy": 99.8, "deck_count": 1}, {"name": "Sythis, Harvest's Hand", "id": "sythis-harvests-hand", "image_uri": "https://cards.scryfall.io/normal/front/0/b/0babfe00-9bad-48fc-b3b1-df8280242fd2.jpg", "inclusion_pct": 9.1, "synergy": 8.9, "deck_count": 1}, {"name": "Falco Spara, Pactweaver", "id": "falco-spara-pactweaver", "image_uri": "https://cards.scryfall.io/normal/front/a/e/ae25db8c-3d10-4196-b002-9d2aabd5f4de.jpg", "inclusion_pct": 50.0, "synergy": 49.8, "deck_count": 1}]}