{"name": "Aetherflux Reservoir", "slug": "aetherflux-reservoir", "scryfall_id": "96b6b2e1-c3e6-464c-8a13-b15deb34e862", "image_uri": "https://cards.scryfall.io/normal/front/9/6/96b6b2e1-c3e6-464c-8a13-b15deb34e862.jpg", "type_line": "Artifact", "total_decks": 18, "total_pct": 1.2, "color_identity": [], "commanders": [{"name": "Lady Octopus, Inspired Inventor", "id": "lady-octopus-inspired-inventor", "image_uri": "https://cards.scryfall.io/normal/front/8/c/8c5f360b-f9a0-46e0-9e8b-58e5b4b0389e.jpg", "inclusion_pct": 42.9, "synergy": 41.7, "deck_count": 3}, {"name": "Trelasarra, Moon Dancer", "id": "trelasarra-moon-dancer", "image_uri": "https://cards.scryfall.io/normal/front/f/6/f6a4b54c-a8fa-464e-a3dd-f3f3a08606f5.jpg", "inclusion_pct": 100.0, "synergy": 98.8, "deck_count": 2}, {"name": "Shorikai, Genesis Engine", "id": "shorikai-genesis-engine", "image_uri": "https://cards.scryfall.io/normal/front/9/6/969ac7dd-f3aa-4888-9ff0-d16a31b5e7a9.jpg", "inclusion_pct": 5.1, "synergy": 3.9, "deck_count": 2}, {"name": "Golos, Tireless Pilgrim", "id": "golos-tireless-pilgrim", "image_uri": "https://cards.scryfall.io/normal/front/1/f/1fa48620-4c3d-4f75-be1f-c12c4aa59f51.jpg", "inclusion_pct": 13.3, "synergy": 12.1, "deck_count": 2}, {"name": "Acererak the Archlich", "id": "acererak-the-archlich", "image_uri": "https://cards.scryfall.io/normal/front/d/d/dd52d0bd-3abd-401c-9f56-ee911613da3b.jpg", "inclusion_pct": 40.0, "synergy": 38.8, "deck_count": 2}, {"name": "Clement, the Worrywort", "id": "clement-the-worrywort", "image_uri": "https://cards.scryfall.io/normal/front/7/0/7028130c-c91d-4bf7-b0b0-450f71107d7a.jpg", "inclusion_pct": 33.3, "synergy": 32.1, "deck_count": 1}, {"name": "Karlov of the Ghost Council", "id": "karlov-of-the-ghost-council", "image_uri": "https://cards.scryfall.io/normal/front/0/9/0970990d-2d74-4fd1-b42e-3401a2154914.jpg", "inclusion_pct": 8.3, "synergy": 7.1, "deck_count": 1}, {"name": "Tatyova, Benthic Druid", "id": "tatyova-benthic-druid", "image_uri": "https://cards.scryfall.io/normal/front/c/d/cd82bff9-8061-48c0-a7c3-fee17acee22a.jpg", "inclusion_pct": 100.0, "synergy": 98.8, "deck_count": 1}, {"name": "Meria, Scholar of Antiquity", "id": "meria-scholar-of-antiquity", "image_uri": "https://cards.scryfall.io/normal/front/3/e/3eedd979-783d-4721-92de-965b77c20576.jpg", "inclusion_pct": 100.0, "synergy": 98.8, "deck_count": 1}, {"name": "Vito, Thorn of the Dusk Rose", "id": "vito-thorn-of-the-dusk-rose", "image_uri": "https://cards.scryfall.io/normal/front/0/f/0fe79ee4-c3f3-4a6b-a967-203ca3b70ee5.jpg", "inclusion_pct": 100.0, "synergy": 98.8, "deck_count": 1}, {"name": "Sai, Master Thopterist", "id": "sai-master-thopterist", "image_uri": "https://cards.scryfall.io/normal/front/a/1/a1091e0e-a179-4241-8be0-ea92d86f4c08.jpg", "inclusion_pct": 25.0, "synergy": 23.8, "deck_count": 1}, {"name": "Jhoira, Weatherlight Captain", "id": "jhoira-weatherlight-captain", "image_uri": "https://cards.scryfall.io/normal/front/4/f/4f77d23d-6257-4dae-b585-29f45f13f2e2.jpg", "inclusion_pct": 100.0, "synergy": 98.8, "deck_count": 1}]}