{"name": "Bushwhack", "slug": "bushwhack", "scryfall_id": "712a0640-d9c8-46fc-b38b-bf20a40fa902", "image_uri": "https://cards.scryfall.io/normal/front/7/1/712a0640-d9c8-46fc-b38b-bf20a40fa902.jpg", "type_line": "Sorcery", "total_decks": 3, "total_pct": 0.2, "color_identity": ["G"], "commanders": [{"name": "Arahbo, Roar of the World", "id": "arahbo-roar-of-the-world", "image_uri": "https://cards.scryfall.io/normal/front/8/1/81dc3d00-97cd-4549-b5a4-15a1e08767f5.jpg", "inclusion_pct": 12.5, "synergy": 12.3, "deck_count": 2}, {"name": "Gargos, Vicious Watcher", "id": "gargos-vicious-watcher", "image_uri": "https://cards.scryfall.io/normal/front/5/7/574057d5-d4a3-4d51-9f53-830d533426b2.jpg", "inclusion_pct": 50.0, "synergy": 49.8, "deck_count": 1}]}