{"name": "Cave-In", "slug": "cave-in", "scryfall_id": "440d9d26-f304-467d-af79-914cc65f082e", "image_uri": "https://cards.scryfall.io/normal/front/4/4/440d9d26-f304-467d-af79-914cc65f082e.jpg", "type_line": "Sorcery", "total_decks": 7, "total_pct": 0.5, "color_identity": ["R"], "commanders": [{"name": "Eris, Roar of the Storm", "id": "eris-roar-of-the-storm", "image_uri": "https://cards.scryfall.io/normal/front/e/2/e2b33794-d124-4c12-ad5a-efef24a0851b.jpg", "inclusion_pct": 18.8, "synergy": 18.3, "deck_count": 3}, {"name": "Feldon, Ronom Excavator", "id": "feldon-ronom-excavator", "image_uri": "https://cards.scryfall.io/normal/front/5/c/5ca4cb0e-63ad-4275-a27f-da476260b467.jpg", "inclusion_pct": 8.7, "synergy": 8.2, "deck_count": 2}, {"name": "Vial Smasher the Fierce", "id": "vial-smasher-the-fierce", "image_uri": "https://cards.scryfall.io/normal/front/c/c/cc7be939-2202-40fe-8899-a05682d76190.jpg", "inclusion_pct": 33.3, "synergy": 32.8, "deck_count": 1}, {"name": "Vivi Ornitier", "id": "vivi-ornitier", "image_uri": "https://cards.scryfall.io/normal/front/a/d/ada6aeb6-8c9f-4498-9326-b4da0fcb19a3.jpg", "inclusion_pct": 9.1, "synergy": 8.6, "deck_count": 1}]}