{"name": "Dread Fugue", "slug": "dread-fugue", "scryfall_id": "0ad4c472-b8ce-4ae0-a6f0-726ea74722c5", "image_uri": "https://cards.scryfall.io/normal/front/0/a/0ad4c472-b8ce-4ae0-a6f0-726ea74722c5.jpg", "type_line": "Sorcery", "total_decks": 18, "total_pct": 1.2, "color_identity": ["B"], "commanders": [{"name": "Hogaak, Arisen Necropolis", "id": "hogaak-arisen-necropolis", "image_uri": "https://cards.scryfall.io/normal/front/0/0/0049e68d-0caf-474f-9523-dad343f1250a.jpg", "inclusion_pct": 17.4, "synergy": 16.2, "deck_count": 4}, {"name": "Inalla, Archmage Ritualist", "id": "inalla-archmage-ritualist", "image_uri": "https://cards.scryfall.io/normal/front/7/c/7c6e803a-451c-4aa6-97a2-400077f32c47.jpg", "inclusion_pct": 33.3, "synergy": 32.1, "deck_count": 3}, {"name": "Sheoldred, the Apocalypse", "id": "sheoldred-the-apocalypse", "image_uri": "https://cards.scryfall.io/normal/front/d/6/d67be074-cdd4-41d9-ac89-0a0456c4e4b2.jpg", "inclusion_pct": 75.0, "synergy": 73.8, "deck_count": 3}, {"name": "Kroxa, Titan of Death's Hunger", "id": "kroxa-titan-of-deaths-hunger", "image_uri": "https://cards.scryfall.io/normal/front/c/e/cee0459b-9aac-4d2f-abe4-4d5fedde7eb8.jpg", "inclusion_pct": 28.6, "synergy": 27.4, "deck_count": 2}, {"name": "Anje Falkenrath", "id": "anje-falkenrath", "image_uri": "https://cards.scryfall.io/normal/front/9/1/913dd06f-ed2f-4128-9c9d-9cd0d8a55425.jpg", "inclusion_pct": 33.3, "synergy": 32.1, "deck_count": 1}, {"name": "Flamewar, Brash Veteran // Flamewar, Streetwise Operative", "id": "flamewar-brash-veteran", "image_uri": "https://cards.scryfall.io/normal/front/8/7/876d9732-9201-4327-8748-7c87ec55453f.jpg", "inclusion_pct": 33.3, "synergy": 32.1, "deck_count": 1}, {"name": "Old Stickfingers", "id": "old-stickfingers", "image_uri": "https://cards.scryfall.io/normal/front/b/2/b203be6f-c565-4d8f-b200-b537569a0292.jpg", "inclusion_pct": 25.0, "synergy": 23.8, "deck_count": 1}, {"name": "Rivaz of the Claw", "id": "rivaz-of-the-claw", "image_uri": "https://cards.scryfall.io/normal/front/9/a/9a47573a-601e-4738-acef-16118289f939.jpg", "inclusion_pct": 50.0, "synergy": 48.8, "deck_count": 1}, {"name": "Anowon, the Ruin Thief", "id": "anowon-the-ruin-thief", "image_uri": "https://cards.scryfall.io/normal/front/b/c/bca84fc4-4710-44c8-b90a-73ef888714d8.jpg", "inclusion_pct": 100.0, "synergy": 98.8, "deck_count": 1}, {"name": "Ertai Resurrected", "id": "ertai-resurrected", "image_uri": "https://cards.scryfall.io/normal/front/7/f/7f7e780e-fbc5-4dc0-b5c7-efcb8645c7c6.jpg", "inclusion_pct": 6.2, "synergy": 5.0, "deck_count": 1}]}