{"name": "Embercleave", "slug": "embercleave", "scryfall_id": "32bee083-859e-407c-99ad-3fb74b1d4233", "image_uri": "https://cards.scryfall.io/normal/front/3/2/32bee083-859e-407c-99ad-3fb74b1d4233.jpg", "type_line": "Legendary Artifact — Equipment", "total_decks": 20, "total_pct": 1.4, "color_identity": ["R"], "commanders": [{"name": "Yoshimaru, Ever Faithful", "id": "yoshimaru-ever-faithful", "image_uri": "https://cards.scryfall.io/normal/front/a/a/aa409269-3698-42a2-8c51-75557b27a6f6.jpg", "inclusion_pct": 50.0, "synergy": 48.6, "deck_count": 11}, {"name": "Tana, the Bloodsower", "id": "tana-the-bloodsower", "image_uri": "https://cards.scryfall.io/normal/front/a/3/a3d8d64f-a403-42a7-881b-4f70e9fe15a2.jpg", "inclusion_pct": 57.1, "synergy": 55.7, "deck_count": 4}, {"name": "Ludevic, Necro-Alchemist", "id": "ludevic-necro-alchemist", "image_uri": "https://cards.scryfall.io/normal/front/f/3/f3e7a886-2593-4e6e-b9da-d7cb417cba08.jpg", "inclusion_pct": 30.0, "synergy": 28.6, "deck_count": 3}, {"name": "Samut, Vizier of Naktamun", "id": "samut-vizier-of-naktamun", "image_uri": "https://cards.scryfall.io/normal/front/7/0/70c868b7-1600-449a-abd2-9836bce0e1f1.jpg", "inclusion_pct": 50.0, "synergy": 48.6, "deck_count": 2}, {"name": "Dargo, the Shipwrecker", "id": "dargo-the-shipwrecker", "image_uri": "https://cards.scryfall.io/normal/front/a/4/a4e9002d-782c-460e-8f0c-4763fffc9e3e.jpg", "inclusion_pct": 66.7, "synergy": 65.3, "deck_count": 2}, {"name": "Ruby, Daring Tracker", "id": "ruby-daring-tracker", "image_uri": "https://cards.scryfall.io/normal/front/f/f/ffb5786b-6825-4ebf-a1e1-80011340adbb.jpg", "inclusion_pct": 100.0, "synergy": 98.6, "deck_count": 2}, {"name": "Jeska, Thrice Reborn", "id": "jeska-thrice-reborn", "image_uri": "https://cards.scryfall.io/normal/front/2/d/2de336a3-224f-49e0-b4ff-34bf3de398bf.jpg", "inclusion_pct": 100.0, "synergy": 98.6, "deck_count": 1}, {"name": "Merry, Esquire of Rohan", "id": "merry-esquire-of-rohan", "image_uri": "https://cards.scryfall.io/normal/front/b/7/b7c5fe73-1684-4edc-9f9b-976b2246d5ea.jpg", "inclusion_pct": 100.0, "synergy": 98.6, "deck_count": 1}, {"name": "Indoraptor, the Perfect Hybrid", "id": "indoraptor-the-perfect-hybrid", "image_uri": "https://cards.scryfall.io/normal/front/3/8/3826e2af-c134-4dc1-98b5-574b1bda9a98.jpg", "inclusion_pct": 25.0, "synergy": 23.6, "deck_count": 1}, {"name": "Bruse Tarl, Boorish Herder", "id": "bruse-tarl-boorish-herder", "image_uri": "https://cards.scryfall.io/normal/front/1/2/125b552b-45ea-4e0b-94a9-8131c97a04c0.jpg", "inclusion_pct": 10.0, "synergy": 8.6, "deck_count": 1}, {"name": "Scarlet Spider, Ben Reilly", "id": "scarlet-spider-ben-reilly", "image_uri": "https://cards.scryfall.io/normal/front/e/e/ee771581-f867-48d7-9ddb-897a1ffcdf0a.jpg", "inclusion_pct": 50.0, "synergy": 48.6, "deck_count": 1}, {"name": "Jirina Kudro", "id": "jirina-kudro", "image_uri": "https://cards.scryfall.io/normal/front/6/e/6e660d42-f5d3-452a-9662-74e18a1ae9e4.jpg", "inclusion_pct": 100.0, "synergy": 98.6, "deck_count": 1}, {"name": "Kari Zev, Skyship Raider", "id": "kari-zev-skyship-raider", "image_uri": "https://cards.scryfall.io/normal/front/7/2/72495879-39ce-449d-ad2f-ef32ea46f3aa.jpg", "inclusion_pct": 7.7, "synergy": 6.3, "deck_count": 1}]}