{"name": "Footfall Crater", "slug": "footfall-crater", "scryfall_id": "f1b75aac-54e3-4181-bac5-5a142757ec05", "image_uri": "https://cards.scryfall.io/normal/front/f/1/f1b75aac-54e3-4181-bac5-5a142757ec05.jpg", "type_line": "Enchantment — Aura", "total_decks": 10, "total_pct": 0.7, "color_identity": ["R"], "commanders": [{"name": "Asmoranomardicadaistinaculdacar", "id": "asmoranomardicadaistinaculdacar", "image_uri": "https://cards.scryfall.io/normal/front/2/8/2879f780-e17f-4e68-931e-6e45f9df28e1.jpg", "inclusion_pct": 26.3, "synergy": 25.6, "deck_count": 10}]}