{"name": "Future Sight", "slug": "future-sight", "scryfall_id": "c37c7dfa-3ef3-4958-9b54-e96c7483f054", "image_uri": "https://cards.scryfall.io/normal/front/c/3/c37c7dfa-3ef3-4958-9b54-e96c7483f054.jpg", "type_line": "Enchantment", "total_decks": 5, "total_pct": 0.3, "color_identity": ["U"], "commanders": [{"name": "Kinnan, Bonder Prodigy", "id": "kinnan-bonder-prodigy", "image_uri": "https://cards.scryfall.io/normal/front/6/3/63cda4a0-0dff-4edb-ae67-a2b7e2971350.jpg", "inclusion_pct": 9.1, "synergy": 8.8, "deck_count": 2}, {"name": "Golos, Tireless Pilgrim", "id": "golos-tireless-pilgrim", "image_uri": "https://cards.scryfall.io/normal/front/1/f/1fa48620-4c3d-4f75-be1f-c12c4aa59f51.jpg", "inclusion_pct": 6.7, "synergy": 6.4, "deck_count": 1}, {"name": "Elminster", "id": "elminster", "image_uri": "https://cards.scryfall.io/normal/front/0/6/06700514-b19c-4fc8-beb1-2c801f320b25.jpg", "inclusion_pct": 8.3, "synergy": 8.0, "deck_count": 1}, {"name": "Jace, Vryn's Prodigy // Jace, Telepath Unbound", "id": "jace-vryns-prodigy", "image_uri": "https://cards.scryfall.io/normal/front/0/2/02d6d693-f1f3-4317-bcc0-c21fa8490d38.jpg", "inclusion_pct": 100.0, "synergy": 99.7, "deck_count": 1}]}