{"name": "Goldbug, Humanity's Ally // Goldbug, Scrappy Scout", "slug": "goldbug-humanitys-ally", "scryfall_id": "8e4a8db9-ef57-4ea0-952c-1e5d343fb5d9", "image_uri": "https://cards.scryfall.io/normal/front/8/e/8e4a8db9-ef57-4ea0-952c-1e5d343fb5d9.jpg", "type_line": "Legendary Artifact Creature — Robot // Legendary Artifact — Vehicle", "total_decks": 4, "total_pct": 0.3, "color_identity": ["U", "W"], "commanders": [{"name": "Urza, Chief Artificer", "id": "urza-chief-artificer", "image_uri": "https://cards.scryfall.io/normal/front/e/a/ea409050-4296-4b76-a6cd-2896ce1b88e4.jpg", "inclusion_pct": 33.3, "synergy": 33.0, "deck_count": 3}, {"name": "Dennick, Pious Apprentice // Dennick, Pious Apparition", "id": "dennick-pious-apprentice", "image_uri": "https://cards.scryfall.io/normal/front/e/c/ecb54b26-7f0d-4f84-abcc-4dd9bfe57848.jpg", "inclusion_pct": 100.0, "synergy": 99.7, "deck_count": 1}]}