{"name": "Hammer of Nazahn", "slug": "hammer-of-nazahn", "scryfall_id": "fa055f1f-be94-4682-8e4f-f022c95e6d58", "image_uri": "https://cards.scryfall.io/normal/front/f/a/fa055f1f-be94-4682-8e4f-f022c95e6d58.jpg", "type_line": "Legendary Artifact — Equipment", "total_decks": 4, "total_pct": 0.3, "color_identity": [], "commanders": [{"name": "Arahbo, Roar of the World", "id": "arahbo-roar-of-the-world", "image_uri": "https://cards.scryfall.io/normal/front/8/1/81dc3d00-97cd-4549-b5a4-15a1e08767f5.jpg", "inclusion_pct": 12.5, "synergy": 12.2, "deck_count": 2}, {"name": "Balan, Wandering Knight", "id": "balan-wandering-knight", "image_uri": "https://cards.scryfall.io/normal/front/d/7/d7f6da2e-3759-4550-999f-2c0fa6c76c73.jpg", "inclusion_pct": 100.0, "synergy": 99.7, "deck_count": 1}, {"name": "Thrun, Breaker of Silence", "id": "thrun-breaker-of-silence", "image_uri": "https://cards.scryfall.io/normal/front/6/d/6d9f51dd-0393-4b3c-bea5-8f74634ab0e5.jpg", "inclusion_pct": 100.0, "synergy": 99.7, "deck_count": 1}]}