{"name": "Heliod's Intervention", "slug": "heliods-intervention", "scryfall_id": "8f1c16dd-38e9-4974-b570-8678c114a549", "image_uri": "https://cards.scryfall.io/normal/front/8/f/8f1c16dd-38e9-4974-b570-8678c114a549.jpg", "type_line": "Instant", "total_decks": 7, "total_pct": 0.5, "color_identity": ["W"], "commanders": [{"name": "Hope Estheim", "id": "hope-estheim", "image_uri": "https://cards.scryfall.io/normal/front/f/b/fbdb68cc-5516-481a-94c5-59f6c69b8a17.jpg", "inclusion_pct": 100.0, "synergy": 99.5, "deck_count": 1}, {"name": "Will, Scion of Peace", "id": "will-scion-of-peace", "image_uri": "https://cards.scryfall.io/normal/front/1/6/162088ea-5f99-4244-9427-2fdfb2168fc3.jpg", "inclusion_pct": 100.0, "synergy": 99.5, "deck_count": 1}, {"name": "Isperia, Supreme Judge", "id": "isperia-supreme-judge", "image_uri": "https://cards.scryfall.io/normal/front/1/e/1e3b82a7-ebef-4190-9f50-40b992ba89c9.jpg", "inclusion_pct": 100.0, "synergy": 99.5, "deck_count": 1}, {"name": "Hinata, Dawn-Crowned", "id": "hinata-dawn-crowned", "image_uri": "https://cards.scryfall.io/normal/front/f/2/f25aff90-56fd-4f70-bb3b-cabf2900c391.jpg", "inclusion_pct": 50.0, "synergy": 49.5, "deck_count": 1}, {"name": "Shorikai, Genesis Engine", "id": "shorikai-genesis-engine", "image_uri": "https://cards.scryfall.io/normal/front/9/6/969ac7dd-f3aa-4888-9ff0-d16a31b5e7a9.jpg", "inclusion_pct": 2.6, "synergy": 2.1, "deck_count": 1}, {"name": "Go-Shintai of Life's Origin", "id": "go-shintai-of-lifes-origin", "image_uri": "https://cards.scryfall.io/normal/front/9/4/9476fe67-d2d3-4835-8ba6-2a17d18cc141.jpg", "inclusion_pct": 100.0, "synergy": 99.5, "deck_count": 1}, {"name": "Adeline, Resplendent Cathar", "id": "adeline-resplendent-cathar", "image_uri": "https://cards.scryfall.io/normal/front/1/8/18092f68-b96e-4084-9eba-b240d2195d81.jpg", "inclusion_pct": 100.0, "synergy": 99.5, "deck_count": 1}]}