{"name": "Knight of the White Orchid", "slug": "knight-of-the-white-orchid", "scryfall_id": "049a601d-de5c-412c-87a2-69500c08809a", "image_uri": "https://cards.scryfall.io/normal/front/0/4/049a601d-de5c-412c-87a2-69500c08809a.jpg", "type_line": "Creature — Human Knight", "total_decks": 19, "total_pct": 1.3, "color_identity": ["W"], "commanders": [{"name": "Kytheon, Hero of Akros // Gideon, Battle-Forged", "id": "kytheon-hero-of-akros", "image_uri": "https://cards.scryfall.io/normal/front/5/8/58c39df6-b237-40d1-bdcb-2fe5d05392a9.jpg", "inclusion_pct": 100.0, "synergy": 98.7, "deck_count": 9}, {"name": "Sidar Jabari of Zhalfir", "id": "sidar-jabari-of-zhalfir", "image_uri": "https://cards.scryfall.io/normal/front/5/f/5fc707be-9286-4ba1-90f6-475265d19ed2.jpg", "inclusion_pct": 66.7, "synergy": 65.4, "deck_count": 2}, {"name": "Elenda, Saint of Dusk", "id": "elenda-saint-of-dusk", "image_uri": "https://cards.scryfall.io/normal/front/2/4/24955f5f-093c-4d33-b0c1-911cd36032ce.jpg", "inclusion_pct": 33.3, "synergy": 32.0, "deck_count": 2}, {"name": "Phlage, Titan of Fire's Fury", "id": "phlage-titan-of-fires-fury", "image_uri": "https://cards.scryfall.io/normal/front/e/4/e419cd0b-2449-4cc5-9ead-b9e45e271700.jpg", "inclusion_pct": 16.7, "synergy": 15.4, "deck_count": 1}, {"name": "Tomik, Wielder of Law", "id": "tomik-wielder-of-law", "image_uri": "https://cards.scryfall.io/normal/front/2/c/2c5a7550-fe1a-4797-9583-70ab56cfac0d.jpg", "inclusion_pct": 100.0, "synergy": 98.7, "deck_count": 1}, {"name": "Tymna the Weaver", "id": "tymna-the-weaver", "image_uri": "https://cards.scryfall.io/normal/front/b/c/bc7cbe9b-324e-42b8-94e2-36e91cb32163.jpg", "inclusion_pct": 6.7, "synergy": 5.4, "deck_count": 1}, {"name": "Phelia, Exuberant Shepherd", "id": "phelia-exuberant-shepherd", "image_uri": "https://cards.scryfall.io/normal/front/5/5/55707746-da6e-46e5-a5ca-7ac843fdc38e.jpg", "inclusion_pct": 10.0, "synergy": 8.7, "deck_count": 1}, {"name": "Isamaru, Hound of Konda", "id": "isamaru-hound-of-konda", "image_uri": "https://cards.scryfall.io/normal/front/9/e/9e66b0f2-262e-4feb-8ae5-ad1f60b6611c.jpg", "inclusion_pct": 100.0, "synergy": 98.7, "deck_count": 1}, {"name": "Adeline, Resplendent Cathar", "id": "adeline-resplendent-cathar", "image_uri": "https://cards.scryfall.io/normal/front/1/8/18092f68-b96e-4084-9eba-b240d2195d81.jpg", "inclusion_pct": 100.0, "synergy": 98.7, "deck_count": 1}]}