{"name": "Liliana, Death's Majesty", "slug": "liliana-deaths-majesty", "scryfall_id": "b63ae119-f91e-4d0d-8bbd-65350a4d47c4", "image_uri": "https://cards.scryfall.io/normal/front/b/6/b63ae119-f91e-4d0d-8bbd-65350a4d47c4.jpg", "type_line": "Legendary Planeswalker — Liliana", "total_decks": 3, "total_pct": 0.2, "color_identity": ["B"], "commanders": [{"name": "Wilhelt, the Rotcleaver", "id": "wilhelt-the-rotcleaver", "image_uri": "https://cards.scryfall.io/normal/front/2/5/2501a911-d072-436d-ae3b-a5164e3b30aa.jpg", "inclusion_pct": 100.0, "synergy": 99.8, "deck_count": 2}, {"name": "Sefris of the Hidden Ways", "id": "sefris-of-the-hidden-ways", "image_uri": "https://cards.scryfall.io/normal/front/d/3/d30255f6-e058-476a-b377-2ee4c9178ed1.jpg", "inclusion_pct": 100.0, "synergy": 99.8, "deck_count": 1}]}