{"name": "Massacre Wurm", "slug": "massacre-wurm", "scryfall_id": "fce002dc-5fb5-465b-935e-042121f1119d", "image_uri": "https://cards.scryfall.io/normal/front/f/c/fce002dc-5fb5-465b-935e-042121f1119d.jpg", "type_line": "Creature — Phyrexian Wurm", "total_decks": 5, "total_pct": 0.3, "color_identity": ["B"], "commanders": [{"name": "Anje Falkenrath", "id": "anje-falkenrath", "image_uri": "https://cards.scryfall.io/normal/front/9/1/913dd06f-ed2f-4128-9c9d-9cd0d8a55425.jpg", "inclusion_pct": 66.7, "synergy": 66.4, "deck_count": 2}, {"name": "Brimaz, Blight of Oreskos", "id": "brimaz-blight-of-oreskos", "image_uri": "https://cards.scryfall.io/normal/front/f/0/f0d31ae7-8580-402a-a917-3d626a9e1f49.jpg", "inclusion_pct": 100.0, "synergy": 99.7, "deck_count": 1}, {"name": "Kels, Fight Fixer", "id": "kels-fight-fixer", "image_uri": "https://cards.scryfall.io/normal/front/b/7/b70d445b-d3d6-4f7c-b9ea-bed6a26d4a2a.jpg", "inclusion_pct": 100.0, "synergy": 99.7, "deck_count": 1}, {"name": "Gix, Yawgmoth Praetor", "id": "gix-yawgmoth-praetor", "image_uri": "https://cards.scryfall.io/normal/front/2/c/2c76f7e0-37e7-4e87-93a3-a25ba0674645.jpg", "inclusion_pct": 33.3, "synergy": 33.0, "deck_count": 1}]}