{"name": "Mossborn Hydra", "slug": "mossborn-hydra", "scryfall_id": "7054a0d7-396f-40b4-ab24-db591c3b08f0", "image_uri": "https://cards.scryfall.io/normal/front/7/0/7054a0d7-396f-40b4-ab24-db591c3b08f0.jpg", "type_line": "Creature — Elemental Hydra", "total_decks": 8, "total_pct": 0.5, "color_identity": ["G"], "commanders": [{"name": "Tifa Lockhart", "id": "tifa-lockhart", "image_uri": "https://cards.scryfall.io/normal/front/f/b/fb781323-2746-405d-a9b2-e778c037a6e9.jpg", "inclusion_pct": 75.0, "synergy": 74.5, "deck_count": 6}, {"name": "Omnath, Locus of Creation", "id": "omnath-locus-of-creation", "image_uri": "https://cards.scryfall.io/normal/front/4/e/4e4fb50c-a81f-44d3-93c5-fa9a0b37f617.jpg", "inclusion_pct": 2.6, "synergy": 2.1, "deck_count": 1}, {"name": "The Earth King", "id": "the-earth-king", "image_uri": "https://cards.scryfall.io/normal/front/3/6/3687f487-eec1-4979-8008-5c907adafe9d.jpg", "inclusion_pct": 100.0, "synergy": 99.5, "deck_count": 1}]}