{"name": "Raven's Crime", "slug": "ravens-crime", "scryfall_id": "7271436b-897a-4b24-a5d2-d29dbea8c1bf", "image_uri": "https://cards.scryfall.io/normal/front/7/2/7271436b-897a-4b24-a5d2-d29dbea8c1bf.jpg", "type_line": "Sorcery", "total_decks": 5, "total_pct": 0.3, "color_identity": ["B"], "commanders": [{"name": "The Gitrog Monster", "id": "the-gitrog-monster", "image_uri": "https://cards.scryfall.io/normal/front/5/7/5790dd89-2be5-4a77-9450-2d3c1422bfc9.jpg", "inclusion_pct": 28.6, "synergy": 28.3, "deck_count": 2}, {"name": "Tergrid, God of Fright // Tergrid's Lantern", "id": "tergrid-god-of-fright", "image_uri": "https://cards.scryfall.io/normal/front/9/f/9ff4efdf-c0bb-443a-a100-2f3850571e91.jpg", "inclusion_pct": 33.3, "synergy": 33.0, "deck_count": 1}, {"name": "Tourach, Dread Cantor", "id": "tourach-dread-cantor", "image_uri": "https://cards.scryfall.io/normal/front/1/0/1049df04-5452-4c82-a167-de608726b99c.jpg", "inclusion_pct": 33.3, "synergy": 33.0, "deck_count": 1}, {"name": "Aclazotz, Deepest Betrayal // Temple of the Dead", "id": "aclazotz-deepest-betrayal", "image_uri": "https://cards.scryfall.io/normal/front/6/2/627c392c-4d18-4eb2-a4e8-c668f61f5487.jpg", "inclusion_pct": 100.0, "synergy": 99.7, "deck_count": 1}]}