{"name": "Scattered Thoughts", "slug": "scattered-thoughts", "scryfall_id": "dc5c6675-6e0f-427d-9399-a6e7fc6215f1", "image_uri": "https://cards.scryfall.io/normal/front/d/c/dc5c6675-6e0f-427d-9399-a6e7fc6215f1.jpg", "type_line": "Instant", "total_decks": 4, "total_pct": 0.3, "color_identity": ["U"], "commanders": [{"name": "Eris, Roar of the Storm", "id": "eris-roar-of-the-storm", "image_uri": "https://cards.scryfall.io/normal/front/e/2/e2b33794-d124-4c12-ad5a-efef24a0851b.jpg", "inclusion_pct": 18.8, "synergy": 18.5, "deck_count": 3}, {"name": "Ertai Resurrected", "id": "ertai-resurrected", "image_uri": "https://cards.scryfall.io/normal/front/7/f/7f7e780e-fbc5-4dc0-b5c7-efcb8645c7c6.jpg", "inclusion_pct": 6.2, "synergy": 5.9, "deck_count": 1}]}