{"name": "Skyclave Shade", "slug": "skyclave-shade", "scryfall_id": "05347539-de61-4a37-929f-c909e65033f5", "image_uri": "https://cards.scryfall.io/normal/front/0/5/05347539-de61-4a37-929f-c909e65033f5.jpg", "type_line": "Creature — Shade", "total_decks": 4, "total_pct": 0.3, "color_identity": ["B"], "commanders": [{"name": "Grist, Voracious Larva // Grist, the Plague Swarm", "id": "grist-voracious-larva", "image_uri": "https://cards.scryfall.io/normal/front/6/8/68239b41-b7db-4044-b672-6808c2c342ec.jpg", "inclusion_pct": 50.0, "synergy": 49.7, "deck_count": 1}, {"name": "Juri, Master of the Revue", "id": "juri-master-of-the-revue", "image_uri": "https://cards.scryfall.io/normal/front/a/e/aec6b2b7-625a-451d-bc0b-4456f5bf2719.jpg", "inclusion_pct": 7.7, "synergy": 7.4, "deck_count": 1}, {"name": "Judith, the Scourge Diva", "id": "judith-the-scourge-diva", "image_uri": "https://cards.scryfall.io/normal/front/e/4/e4fc28d1-61d5-4a78-8fbb-6566128486ce.jpg", "inclusion_pct": 33.3, "synergy": 33.0, "deck_count": 1}, {"name": "Asmoranomardicadaistinaculdacar", "id": "asmoranomardicadaistinaculdacar", "image_uri": "https://cards.scryfall.io/normal/front/2/8/2879f780-e17f-4e68-931e-6e45f9df28e1.jpg", "inclusion_pct": 2.6, "synergy": 2.3, "deck_count": 1}]}