{"name": "Sojourner's Companion", "slug": "sojourners-companion", "scryfall_id": "8c6af084-eee7-4259-a58b-a866e0cf171b", "image_uri": "https://cards.scryfall.io/normal/front/8/c/8c6af084-eee7-4259-a58b-a866e0cf171b.jpg", "type_line": "Artifact Creature — Salamander", "total_decks": 19, "total_pct": 1.3, "color_identity": [], "commanders": [{"name": "Imskir Iron-Eater", "id": "imskir-iron-eater", "image_uri": "https://cards.scryfall.io/normal/front/5/4/541209fa-38b6-4d61-a72d-26bfb6ad5ead.jpg", "inclusion_pct": 78.6, "synergy": 77.3, "deck_count": 11}, {"name": "The Reality Chip", "id": "the-reality-chip", "image_uri": "https://cards.scryfall.io/normal/front/d/8/d859de3a-0be1-4e66-b438-1c3d4ee756cd.jpg", "inclusion_pct": 26.3, "synergy": 25.0, "deck_count": 5}, {"name": "Winter, Cursed Rider", "id": "winter-cursed-rider", "image_uri": "https://cards.scryfall.io/normal/front/5/f/5f93e48d-4681-4354-aa85-493a48287233.jpg", "inclusion_pct": 100.0, "synergy": 98.7, "deck_count": 1}, {"name": "Urza, Chief Artificer", "id": "urza-chief-artificer", "image_uri": "https://cards.scryfall.io/normal/front/e/a/ea409050-4296-4b76-a6cd-2896ce1b88e4.jpg", "inclusion_pct": 11.1, "synergy": 9.8, "deck_count": 1}, {"name": "Lady Octopus, Inspired Inventor", "id": "lady-octopus-inspired-inventor", "image_uri": "https://cards.scryfall.io/normal/front/8/c/8c5f360b-f9a0-46e0-9e8b-58e5b4b0389e.jpg", "inclusion_pct": 14.3, "synergy": 13.0, "deck_count": 1}]}