{"name": "Sphinx's Revelation", "slug": "sphinxs-revelation", "scryfall_id": "5579d2d6-b34b-44a2-8b72-9f18938a18a0", "image_uri": "https://cards.scryfall.io/normal/front/5/5/5579d2d6-b34b-44a2-8b72-9f18938a18a0.jpg", "type_line": "Instant", "total_decks": 6, "total_pct": 0.4, "color_identity": ["U", "W"], "commanders": [{"name": "Oloro, Ageless Ascetic", "id": "oloro-ageless-ascetic", "image_uri": "https://cards.scryfall.io/normal/front/a/b/abf8df47-405c-42d8-be9e-0f0d0a49589b.jpg", "inclusion_pct": 33.3, "synergy": 32.9, "deck_count": 2}, {"name": "Queza, Augur of Agonies", "id": "queza-augur-of-agonies", "image_uri": "https://cards.scryfall.io/normal/front/8/b/8be62891-93fa-4642-ad44-8c8695a9c960.jpg", "inclusion_pct": 100.0, "synergy": 99.6, "deck_count": 1}, {"name": "Dragonlord Ojutai", "id": "dragonlord-ojutai", "image_uri": "https://cards.scryfall.io/normal/front/0/1/019728bc-7d37-4384-81e5-97c47660c092.jpg", "inclusion_pct": 50.0, "synergy": 49.6, "deck_count": 1}, {"name": "Urza, Chief Artificer", "id": "urza-chief-artificer", "image_uri": "https://cards.scryfall.io/normal/front/e/a/ea409050-4296-4b76-a6cd-2896ce1b88e4.jpg", "inclusion_pct": 11.1, "synergy": 10.7, "deck_count": 1}, {"name": "Grand Arbiter Augustin IV", "id": "grand-arbiter-augustin-iv", "image_uri": "https://cards.scryfall.io/normal/front/a/4/a49ce8ee-8abe-4973-ae6e-a97e20836d05.jpg", "inclusion_pct": 100.0, "synergy": 99.6, "deck_count": 1}]}