{"name": "The Mycosynth Gardens", "slug": "the-mycosynth-gardens", "scryfall_id": "5a931463-25f6-4e31-95b4-bb4a9388009b", "image_uri": "https://cards.scryfall.io/normal/front/5/a/5a931463-25f6-4e31-95b4-bb4a9388009b.jpg", "type_line": "Land — Sphere", "total_decks": 12, "total_pct": 0.8, "color_identity": [], "commanders": [{"name": "The Reality Chip", "id": "the-reality-chip", "image_uri": "https://cards.scryfall.io/normal/front/d/8/d859de3a-0be1-4e66-b438-1c3d4ee756cd.jpg", "inclusion_pct": 15.8, "synergy": 15.0, "deck_count": 3}, {"name": "Phenax, God of Deception", "id": "phenax-god-of-deception", "image_uri": "https://cards.scryfall.io/normal/front/8/d/8dfcb129-4665-40e4-b5cb-a79f3f40ae5c.jpg", "inclusion_pct": 100.0, "synergy": 99.2, "deck_count": 1}, {"name": "Imskir Iron-Eater", "id": "imskir-iron-eater", "image_uri": "https://cards.scryfall.io/normal/front/5/4/541209fa-38b6-4d61-a72d-26bfb6ad5ead.jpg", "inclusion_pct": 7.1, "synergy": 6.3, "deck_count": 1}, {"name": "Karlov of the Ghost Council", "id": "karlov-of-the-ghost-council", "image_uri": "https://cards.scryfall.io/normal/front/0/9/0970990d-2d74-4fd1-b42e-3401a2154914.jpg", "inclusion_pct": 8.3, "synergy": 7.5, "deck_count": 1}, {"name": "Sen Triplets", "id": "sen-triplets", "image_uri": "https://cards.scryfall.io/normal/front/1/3/13ac5292-9817-4f5d-b3fa-611f9ba44443.jpg", "inclusion_pct": 100.0, "synergy": 99.2, "deck_count": 1}, {"name": "Daretti, Scrap Savant", "id": "daretti-scrap-savant", "image_uri": "https://cards.scryfall.io/normal/front/7/c/7cb9d4a0-66bd-454d-b676-80192a96c723.jpg", "inclusion_pct": 50.0, "synergy": 49.2, "deck_count": 1}, {"name": "Isperia, Supreme Judge", "id": "isperia-supreme-judge", "image_uri": "https://cards.scryfall.io/normal/front/1/e/1e3b82a7-ebef-4190-9f50-40b992ba89c9.jpg", "inclusion_pct": 100.0, "synergy": 99.2, "deck_count": 1}, {"name": "Kinnan, Bonder Prodigy", "id": "kinnan-bonder-prodigy", "image_uri": "https://cards.scryfall.io/normal/front/6/3/63cda4a0-0dff-4edb-ae67-a2b7e2971350.jpg", "inclusion_pct": 4.5, "synergy": 3.7, "deck_count": 1}, {"name": "Wilson, Refined Grizzly", "id": "wilson-refined-grizzly", "image_uri": "https://cards.scryfall.io/normal/front/f/b/fb3ebc0c-ae58-46c9-addc-a91d32201a95.jpg", "inclusion_pct": 20.0, "synergy": 19.2, "deck_count": 1}, {"name": "Folk Hero", "id": "folk-hero", "image_uri": "https://cards.scryfall.io/normal/front/a/8/a8b3aae8-fc36-45ed-84ed-efb8f543cada.jpg", "inclusion_pct": 100.0, "synergy": 99.2, "deck_count": 1}, {"name": "Tamiyo, Inquisitive Student // Tamiyo, Seasoned Scholar", "id": "tamiyo-inquisitive-student", "image_uri": "https://cards.scryfall.io/normal/front/2/a/2a717b98-cdac-416d-bf6c-f6b6638e65d1.jpg", "inclusion_pct": 7.1, "synergy": 6.3, "deck_count": 1}]}