{"name": "Tidehollow Sculler", "slug": "tidehollow-sculler", "scryfall_id": "09521f23-52d6-482d-9f3b-c4d12fcc08cc", "image_uri": "https://cards.scryfall.io/normal/front/0/9/09521f23-52d6-482d-9f3b-c4d12fcc08cc.jpg", "type_line": "Artifact Creature — Zombie", "total_decks": 39, "total_pct": 2.6, "color_identity": ["B", "W"], "commanders": [{"name": "Raffine, Scheming Seer", "id": "raffine-scheming-seer", "image_uri": "https://cards.scryfall.io/normal/front/7/1/716a44b4-f6b0-4f14-a270-6442aed3251f.jpg", "inclusion_pct": 48.0, "synergy": 45.4, "deck_count": 12}, {"name": "Urza, Chief Artificer", "id": "urza-chief-artificer", "image_uri": "https://cards.scryfall.io/normal/front/e/a/ea409050-4296-4b76-a6cd-2896ce1b88e4.jpg", "inclusion_pct": 55.6, "synergy": 53.0, "deck_count": 5}, {"name": "Karlov of the Ghost Council", "id": "karlov-of-the-ghost-council", "image_uri": "https://cards.scryfall.io/normal/front/0/9/0970990d-2d74-4fd1-b42e-3401a2154914.jpg", "inclusion_pct": 33.3, "synergy": 30.7, "deck_count": 4}, {"name": "Liesa, Shroud of Dusk", "id": "liesa-shroud-of-dusk", "image_uri": "https://cards.scryfall.io/normal/front/e/3/e32453a1-1fd9-4bda-aaa8-7c287e4c2587.jpg", "inclusion_pct": 100.0, "synergy": 97.4, "deck_count": 2}, {"name": "Amalia Benavides Aguirre", "id": "amalia-benavides-aguirre", "image_uri": "https://cards.scryfall.io/normal/front/9/a/9acf80a5-f2ca-45b4-aca8-fbc690e35401.jpg", "inclusion_pct": 33.3, "synergy": 30.7, "deck_count": 2}, {"name": "Ketramose, the New Dawn", "id": "ketramose-the-new-dawn", "image_uri": "https://cards.scryfall.io/normal/front/c/f/cffae8d0-7b4e-42ed-8124-24a86b38f490.jpg", "inclusion_pct": 20.0, "synergy": 17.4, "deck_count": 2}, {"name": "Isshin, Two Heavens as One", "id": "isshin-two-heavens-as-one", "image_uri": "https://cards.scryfall.io/normal/front/a/0/a062a004-984e-4b62-960c-af7288f7a3e9.jpg", "inclusion_pct": 100.0, "synergy": 97.4, "deck_count": 1}, {"name": "Teysa, Orzhov Scion", "id": "teysa-orzhov-scion", "image_uri": "https://cards.scryfall.io/normal/front/9/e/9eb856e6-8f63-4048-9818-cc3e65748855.jpg", "inclusion_pct": 100.0, "synergy": 97.4, "deck_count": 1}, {"name": "Tomik, Wielder of Law", "id": "tomik-wielder-of-law", "image_uri": "https://cards.scryfall.io/normal/front/2/c/2c5a7550-fe1a-4797-9583-70ab56cfac0d.jpg", "inclusion_pct": 100.0, "synergy": 97.4, "deck_count": 1}, {"name": "Tazri, Beacon of Unity", "id": "tazri-beacon-of-unity", "image_uri": "https://cards.scryfall.io/normal/front/d/4/d4b79138-5728-4541-9ea5-dce1a5ae7e6a.jpg", "inclusion_pct": 100.0, "synergy": 97.4, "deck_count": 1}, {"name": "Tymna the Weaver", "id": "tymna-the-weaver", "image_uri": "https://cards.scryfall.io/normal/front/b/c/bc7cbe9b-324e-42b8-94e2-36e91cb32163.jpg", "inclusion_pct": 6.7, "synergy": 4.1, "deck_count": 1}, {"name": "Thalia and The Gitrog Monster", "id": "thalia-and-the-gitrog-monster", "image_uri": "https://cards.scryfall.io/normal/front/4/3/43c4eb73-7e50-4c22-8fa6-c770152ebdaf.jpg", "inclusion_pct": 25.0, "synergy": 22.4, "deck_count": 1}, {"name": "Kenrith, the Returned King", "id": "kenrith-the-returned-king", "image_uri": "https://cards.scryfall.io/normal/front/5/6/56c1227e-bea7-47cb-bbec-389a3d585af5.jpg", "inclusion_pct": 100.0, "synergy": 97.4, "deck_count": 1}, {"name": "Niv-Mizzet Reborn", "id": "niv-mizzet-reborn", "image_uri": "https://cards.scryfall.io/normal/front/c/f/cf0d7769-d98e-4cf2-900e-11dc74142c0d.jpg", "inclusion_pct": 25.0, "synergy": 22.4, "deck_count": 1}, {"name": "Anafenza, the Foremost", "id": "anafenza-the-foremost", "image_uri": "https://cards.scryfall.io/normal/front/c/8/c8b432a7-53da-4480-b571-e6feb1364a3a.jpg", "inclusion_pct": 50.0, "synergy": 47.4, "deck_count": 1}, {"name": "Greasefang, Okiba Boss", "id": "greasefang-okiba-boss", "image_uri": "https://cards.scryfall.io/normal/front/5/6/56a0d43b-4d38-40a7-be6c-8324ab3bf773.jpg", "inclusion_pct": 25.0, "synergy": 22.4, "deck_count": 1}, {"name": "Zahur, Glory's Past", "id": "zahur-glorys-past", "image_uri": "https://cards.scryfall.io/normal/front/3/1/31944ea5-045d-481d-9aff-3c7ed663813a.jpg", "inclusion_pct": 100.0, "synergy": 97.4, "deck_count": 1}, {"name": "Elas il-Kor, Sadistic Pilgrim", "id": "elas-il-kor-sadistic-pilgrim", "image_uri": "https://cards.scryfall.io/normal/front/1/c/1c3f0ffe-cf51-4c30-8cd5-9e3c7e92c019.jpg", "inclusion_pct": 25.0, "synergy": 22.4, "deck_count": 1}]}