{"name": "Tolaria West", "slug": "tolaria-west", "scryfall_id": "7adede7f-ee9b-48b7-98cb-9672d36e8a0c", "image_uri": "https://cards.scryfall.io/normal/front/7/a/7adede7f-ee9b-48b7-98cb-9672d36e8a0c.jpg", "type_line": "Land", "total_decks": 85, "total_pct": 5.7, "color_identity": ["U"], "commanders": [{"name": "The Reality Chip", "id": "the-reality-chip", "image_uri": "https://cards.scryfall.io/normal/front/d/8/d859de3a-0be1-4e66-b438-1c3d4ee756cd.jpg", "inclusion_pct": 100.0, "synergy": 94.3, "deck_count": 19}, {"name": "Kinnan, Bonder Prodigy", "id": "kinnan-bonder-prodigy", "image_uri": "https://cards.scryfall.io/normal/front/6/3/63cda4a0-0dff-4edb-ae67-a2b7e2971350.jpg", "inclusion_pct": 68.2, "synergy": 62.5, "deck_count": 15}, {"name": "Shorikai, Genesis Engine", "id": "shorikai-genesis-engine", "image_uri": "https://cards.scryfall.io/normal/front/9/6/969ac7dd-f3aa-4888-9ff0-d16a31b5e7a9.jpg", "inclusion_pct": 30.8, "synergy": 25.1, "deck_count": 12}, {"name": "Golos, Tireless Pilgrim", "id": "golos-tireless-pilgrim", "image_uri": "https://cards.scryfall.io/normal/front/1/f/1fa48620-4c3d-4f75-be1f-c12c4aa59f51.jpg", "inclusion_pct": 60.0, "synergy": 54.3, "deck_count": 9}, {"name": "Iron Man, Titan of Innovation", "id": "iron-man-titan-of-innovation", "image_uri": "https://cards.scryfall.io/normal/front/7/5/7542b1d1-e34d-46dc-af24-1b718034c0e4.jpg", "inclusion_pct": 100.0, "synergy": 94.3, "deck_count": 4}, {"name": "Lady Octopus, Inspired Inventor", "id": "lady-octopus-inspired-inventor", "image_uri": "https://cards.scryfall.io/normal/front/8/c/8c5f360b-f9a0-46e0-9e8b-58e5b4b0389e.jpg", "inclusion_pct": 57.1, "synergy": 51.4, "deck_count": 4}, {"name": "Tamiyo, Inquisitive Student // Tamiyo, Seasoned Scholar", "id": "tamiyo-inquisitive-student", "image_uri": "https://cards.scryfall.io/normal/front/2/a/2a717b98-cdac-416d-bf6c-f6b6638e65d1.jpg", "inclusion_pct": 21.4, "synergy": 15.7, "deck_count": 3}, {"name": "Sai, Master Thopterist", "id": "sai-master-thopterist", "image_uri": "https://cards.scryfall.io/normal/front/a/1/a1091e0e-a179-4241-8be0-ea92d86f4c08.jpg", "inclusion_pct": 75.0, "synergy": 69.3, "deck_count": 3}, {"name": "Urza, Chief Artificer", "id": "urza-chief-artificer", "image_uri": "https://cards.scryfall.io/normal/front/e/a/ea409050-4296-4b76-a6cd-2896ce1b88e4.jpg", "inclusion_pct": 22.2, "synergy": 16.5, "deck_count": 2}, {"name": "Galazeth Prismari", "id": "galazeth-prismari", "image_uri": "https://cards.scryfall.io/normal/front/2/6/265b9185-9033-4e57-a312-adcc91903aec.jpg", "inclusion_pct": 66.7, "synergy": 61.0, "deck_count": 2}, {"name": "Estrid, the Masked", "id": "estrid-the-masked", "image_uri": "https://cards.scryfall.io/normal/front/3/3/3340b83e-72dc-42e2-9f93-92f732c047df.jpg", "inclusion_pct": 66.7, "synergy": 61.0, "deck_count": 2}, {"name": "Uro, Titan of Nature's Wrath", "id": "uro-titan-of-natures-wrath", "image_uri": "https://cards.scryfall.io/normal/front/a/0/a0b6a71e-56cb-4d25-8f2b-7a4f1b60900d.jpg", "inclusion_pct": 6.9, "synergy": 1.2, "deck_count": 2}, {"name": "Hope Estheim", "id": "hope-estheim", "image_uri": "https://cards.scryfall.io/normal/front/f/b/fbdb68cc-5516-481a-94c5-59f6c69b8a17.jpg", "inclusion_pct": 100.0, "synergy": 94.3, "deck_count": 1}, {"name": "Mm'menon, the Right Hand", "id": "mmmenon-the-right-hand", "image_uri": "https://cards.scryfall.io/normal/front/8/2/82add0a0-e402-4b31-b101-81c0bf332015.jpg", "inclusion_pct": 100.0, "synergy": 94.3, "deck_count": 1}, {"name": "God-Eternal Kefnet", "id": "god-eternal-kefnet", "image_uri": "https://cards.scryfall.io/normal/front/5/e/5e14060f-9167-4e28-a053-77689e066e30.jpg", "inclusion_pct": 100.0, "synergy": 94.3, "deck_count": 1}, {"name": "Tatyova, Benthic Druid", "id": "tatyova-benthic-druid", "image_uri": "https://cards.scryfall.io/normal/front/c/d/cd82bff9-8061-48c0-a7c3-fee17acee22a.jpg", "inclusion_pct": 100.0, "synergy": 94.3, "deck_count": 1}, {"name": "Akiri, Line-Slinger", "id": "akiri-line-slinger", "image_uri": "https://cards.scryfall.io/normal/front/3/b/3b951e0c-a4dd-4a20-87c6-eaa947e33aa4.jpg", "inclusion_pct": 25.0, "synergy": 19.3, "deck_count": 1}, {"name": "Silas Renn, Seeker Adept", "id": "silas-renn-seeker-adept", "image_uri": "https://cards.scryfall.io/normal/front/4/e/4e3fe912-1374-47c7-b73f-89ef55c479c1.jpg", "inclusion_pct": 14.3, "synergy": 8.6, "deck_count": 1}, {"name": "Teferi, Temporal Archmage", "id": "teferi-temporal-archmage", "image_uri": "https://cards.scryfall.io/normal/front/3/6/368c6e60-804c-447c-bc2b-ac9dc4cab5e7.jpg", "inclusion_pct": 25.0, "synergy": 19.3, "deck_count": 1}, {"name": "Wernog, Rider's Chaplain", "id": "wernog-riders-chaplain", "image_uri": "https://cards.scryfall.io/normal/front/2/5/25a4af68-6e5e-4b44-9c1c-25ecdbd555b5.jpg", "inclusion_pct": 33.3, "synergy": 27.6, "deck_count": 1}, {"name": "Bjorna, Nightfall Alchemist", "id": "bjorna-nightfall-alchemist", "image_uri": "https://cards.scryfall.io/normal/front/8/3/83b0b716-bcb0-4044-b64a-354e3cbbd563.jpg", "inclusion_pct": 50.0, "synergy": 44.3, "deck_count": 1}, {"name": "Flubs, the Fool", "id": "flubs-the-fool", "image_uri": "https://cards.scryfall.io/normal/front/4/1/41e58eb8-e5b9-4ef6-be1f-00e28cebb998.jpg", "inclusion_pct": 100.0, "synergy": 94.3, "deck_count": 1}]}